<Event class="edu.usc.enl.dynamicmeasurement.model.event.AddTraceTaskEvent" time="8">
    <Property name="task1"
              value="edu.usc.enl.dynamicmeasurement.algorithms.tasks.multitask.multiswitch.separateallocation.MultiSwitchTask">
        <Property name="User"
                  value="edu.usc.enl.dynamicmeasurement.algorithms.tasks.superspreader.SSPacketUser">
            <Property name="Algorithm"
                      value="edu.usc.enl.dynamicmeasurement.algorithms.tasks.superspreader.sketch.hierarchicalcm.SSCountMinMultiSwitch3">
                <Property name="Threshold" value="200"/>
                <Property name="Filter" value="0_______________________________"/>
                <Property name="WildcardNum" value="0"/>
				<Property name="CardinalityCounter" value="edu.usc.enl.dynamicmeasurement.algorithms.tasks.superspreader.sketch.hierarchicalcm.cardinlaitycounter.HyperLogLog">
						<Property name="Precision" value="4"/>
					</Property>
            </Property>
			<Property name="KeyField" value="DstIP"/>
        </Property>
    </Property>
</Event>
